buildarr_prowlarr/__init__.py
buildarr_prowlarr/api.py
buildarr_prowlarr/cli.py
buildarr_prowlarr/config/__init__.py
buildarr_prowlarr/config/settings/__init__.py
buildarr_prowlarr/config/settings/apps/__init__.py
buildarr_prowlarr/config/settings/apps/applications.py
buildarr_prowlarr/config/settings/apps/sync_profiles.py
buildarr_prowlarr/config/settings/download_clients/__init__.py
buildarr_prowlarr/config/settings/download_clients/base.py
buildarr_prowlarr/config/settings/download_clients/torrent.py
buildarr_prowlarr/config/settings/download_clients/usenet.py
buildarr_prowlarr/config/settings/general.py
buildarr_prowlarr/config/settings/indexers/__init__.py
buildarr_prowlarr/config/settings/indexers/indexers.py
buildarr_prowlarr/config/settings/indexers/proxies.py
buildarr_prowlarr/config/settings/notifications.py
buildarr_prowlarr/config/settings/tags.py
buildarr_prowlarr/config/settings/ui.py
buildarr_prowlarr/config/types.py
buildarr_prowlarr/exceptions.py
buildarr_prowlarr/manager.py
buildarr_prowlarr/plugin.py
buildarr_prowlarr/py.typed
buildarr_prowlarr/secrets.py
buildarr_prowlarr/types.py
buildarr_prowlarr/util.py
buildarr_prowlarr-0.5.3.dist-info/LICENSE
buildarr_prowlarr-0.5.3.dist-info/METADATA
buildarr_prowlarr-0.5.3.dist-info/WHEEL
buildarr_prowlarr-0.5.3.dist-info/entry_points.txt
buildarr_prowlarr-0.5.3.dist-info/RECORD
