Metadata-Version: 2.1
Name: buildarr-prowlarr
Version: 0.5.3
Summary: Prowlarr indexer manager plugin for Buildarr
Home-page: https://buildarr.github.io
License: GPL-3.0-or-later
Keywords: buildarr,prowlarr,lazylibrarian,lidarr,mylar,radarr,readarr,sonarr,whisparr
Author: Callum Dickinson
Author-email: callum.dickinson.nz@gmail.com
Requires-Python: >=3.8,<4.0
Classifier: Development Status :: 3 - Alpha
Classifier: Framework :: Pydantic
Classifier: Intended Audience :: End Users/Desktop
Classifier: License :: OSI Approved :: GNU General Public License v3 or later (GPLv3+)
Classifier: Natural Language :: English
Classifier: Operating System :: OS Independent
Classifier: Programming Language :: Python :: 3
Classifier: Programming Language :: Python :: 3.8
Classifier: Programming Language :: Python :: 3.9
Classifier: Programming Language :: Python :: 3.10
Classifier: Programming Language :: Python :: 3.11
Classifier: Programming Language :: Python :: 3.12
Classifier: Topic :: System :: Systems Administration
Classifier: Typing :: Typed
Provides-Extra: radarr
Provides-Extra: sonarr
Requires-Dist: buildarr (>=0.7.0,<0.8.0)
Requires-Dist: buildarr-radarr (>=0.2.0) ; extra == "radarr"
Requires-Dist: buildarr-sonarr (>=0.6.0) ; extra == "sonarr"
Requires-Dist: json5 (>=0.9.7)
Requires-Dist: packaging
Requires-Dist: prowlarr-py (>=0.4.1,<0.5.0)
Project-URL: Changes, https://buildarr.github.io/plugins/prowlarr/release-notes
Project-URL: Documentation, https://buildarr.github.io/plugins/prowlarr
Project-URL: Issue Tracker, https://github.com/buildarr/buildarr-prowlarr/issues
Project-URL: Repository, https://github.com/buildarr/buildarr-prowlarr
